open_analytics/__init__.py
open_analytics/__version__.py
open_analytics/open_analytics.py
open_analytics_elliottmurray-0.0.2.dist-info/LICENSE
open_analytics_elliottmurray-0.0.2.dist-info/METADATA
open_analytics_elliottmurray-0.0.2.dist-info/WHEEL
open_analytics_elliottmurray-0.0.2.dist-info/top_level.txt
open_analytics_elliottmurray-0.0.2.dist-info/RECORD
