Metadata-Version: 2.1
Name: open-analytics-elliottmurray
Version: 0.0.2
Summary: Our stats collector for python
Home-page: https://github.com/elliottmurray/python_sdk
Author: Elliott Murray
Author-email: elliottmurray@gmail.com
License: UNKNOWN
Platform: UNKNOWN
Classifier: Programming Language :: Python :: 3
Classifier: License :: OSI Approved :: MIT License
Classifier: Operating System :: OS Independent
Requires-Python: >=3.4
Requires-Dist: requests (>=2.5.0)
Requires-Dist: six (>=1.9.0)
